anytype/__init__.py
anytype-0.0.0.dist-info/WHEEL
anytype-0.0.0.dist-info/METADATA
anytype-0.0.0.dist-info/RECORD
