Metadata-Version: 2.1
Name: anytype
Version: 0.0.0
Summary: Preserving a name for anytype.io library for Python,
License: MIT
Author: Bobronium
Author-email: appkiller16@gmail.com
Requires-Python: >=3.10,<4.0
Classifier: License :: OSI Approved :: MIT License
Classifier: Programming Language :: Python :: 3
Classifier: Programming Language :: Python :: 3.10
